HISTORY.rst
LICENSE.md
MANIFEST.in
README.rst
setup.py
django_celery_progressbar/__init__.py
django_celery_progressbar/app_settings.py
django_celery_progressbar/apps.py
django_celery_progressbar/bars.py
django_celery_progressbar/exceptions.py
django_celery_progressbar/models.py
django_celery_progressbar.egg-info/PKG-INFO
django_celery_progressbar.egg-info/SOURCES.txt
django_celery_progressbar.egg-info/dependency_links.txt
django_celery_progressbar.egg-info/requires.txt
django_celery_progressbar.egg-info/top_level.txt
django_celery_progressbar/migrations/0001_initial.py
django_celery_progressbar/migrations/__init__.py
tests/__init__.py
tests/settings.py
tests/tests.py